windscribe/__init__.py
windscribe/windscribe.py
python_windscribe_cli_wrapper-2021.10.7.dist-info/METADATA
python_windscribe_cli_wrapper-2021.10.7.dist-info/WHEEL
python_windscribe_cli_wrapper-2021.10.7.dist-info/top_level.txt
python_windscribe_cli_wrapper-2021.10.7.dist-info/RECORD
